biuR/__init__.py
biuR/_nbdev.py
biuR/converter.py
biuR/wrapper.py
biur-0.0.1.dist-info/LICENSE
biur-0.0.1.dist-info/METADATA
biur-0.0.1.dist-info/WHEEL
biur-0.0.1.dist-info/entry_points.txt
biur-0.0.1.dist-info/top_level.txt
biur-0.0.1.dist-info/RECORD
