Metadata-Version: 2.1
Name: biur
Version: 0.0.1
Summary: An extract of the BIU R functionality, without any dependency on biu
Home-page: https://github.com/hgzech/biur/tree/main/
Author: hgzech
Author-email: hilmarzech@gmail.com
License: Apache Software License 2.0
Keywords: Python R
Platform: UNKNOWN
Classifier: Development Status :: 3 - Alpha
Classifier: Intended Audience :: Developers
Classifier: Natural Language :: English
Classifier: Programming Language :: Python :: 3.6
Classifier: Programming Language :: Python :: 3.7
Classifier: Programming Language :: Python :: 3.8
Classifier: License :: OSI Approved :: Apache Software License
Requires-Python: >=3.6
License-File: LICENSE
Requires-Dist: rpy2
Requires-Dist: numpy
Requires-Dist: pandas
Requires-Dist: matplotlib
